autogen_http_runtime/runtimes/http/__init__.py
autogen_http_runtime/runtimes/http/_json_rpc.py
autogen_http_runtime/runtimes/http/_worker_runtime.py
autogen_http_runtime/runtimes/http/_worker_runtime_server.py
autogen_http_runtime/runtimes/http/_worker_runtime_service.py
autogen_http_runtime-0.1.0.dist-info/METADATA
autogen_http_runtime-0.1.0.dist-info/WHEEL
autogen_http_runtime-0.1.0.dist-info/RECORD
