Metadata-Version: 2.4
Name: autogen-http-runtime
Version: 0.1.0
Summary: HTTP runtime for Autogen core
Classifier: License :: OSI Approved :: MIT License
Classifier: Operating System :: OS Independent
Classifier: Programming Language :: Python :: 3
Requires-Python: >=3.10
Requires-Dist: autogen-core>=0.5.7
Requires-Dist: fastapi>=0.115.12
Requires-Dist: httpx>=0.28.1
Requires-Dist: uvicorn[standard]>=0.34.3
Requires-Dist: websockets>=15.0.1
